{"errors":[],"warnings":[],"namedChunkGroups":{"polyfill":{"chunks":[0,4],"assets":["webpack-runtime-fe205c70b7653360bf7e.js","webpack-runtime-fe205c70b7653360bf7e.js.map","polyfill-b10081dcee119dac8324.js","polyfill-b10081dcee119dac8324.js.map"],"children":{},"childAssets":{}},"app":{"chunks":[0,3,1],"assets":["webpack-runtime-fe205c70b7653360bf7e.js","webpack-runtime-fe205c70b7653360bf7e.js.map","framework-24ec06e6f922b5f67264.js","framework-24ec06e6f922b5f67264.js.map","app-7b2d3288ae0ff31a0f70.js","app-7b2d3288ae0ff31a0f70.js.map"],"children":{},"childAssets":{}},"component---src-pages-index-tsx":{"chunks":[5,2],"assets":["styles.eaf811c609fbfbc095ec.css","styles-f1e0270e5d65cc2e9fc3.js","styles-f1e0270e5d65cc2e9fc3.js.map","component---src-pages-index-tsx-a7533caf947b3548fbee.js","component---src-pages-index-tsx-a7533caf947b3548fbee.js.map"],"children":{},"childAssets":{}}},"assetsByChunkName":{"polyfill":["webpack-runtime-fe205c70b7653360bf7e.js","polyfill-b10081dcee119dac8324.js"],"app":["webpack-runtime-fe205c70b7653360bf7e.js","framework-24ec06e6f922b5f67264.js","app-7b2d3288ae0ff31a0f70.js"],"component---src-pages-index-tsx":["styles.eaf811c609fbfbc095ec.css","styles-f1e0270e5d65cc2e9fc3.js","component---src-pages-index-tsx-a7533caf947b3548fbee.js"]}}